{
  "assets": [
    {
      "asset_id": "ANTONIVSKYI_ROAD_BRIDGE_2022_07_27",
      "name_en": "Antonivskyi Road Bridge over the Dnipro, Kherson Oblast",
      "name_uk": "Антонівський автодорожній міст",
      "lat": 46.781,
      "lon": 32.749,
      "oblast": "Kherson",
      "sector": "transport_and_ports",
      "lifecycle": "documented",
      "destruction_level": "destroyed",
      "rebuildability": "frontline_adjacent",
      "re_damage_count": 3,
      "pending_methodology": false,
      "financing_class": "concessional_led",
      "cost_baseline_low": 470,
      "cost_baseline_cen": 1188,
      "cost_baseline_high": 1906,
      "cost_cc_low": 541,
      "cost_cc_cen": 1461,
      "cost_cc_high": 2382,
      "cost_bbb_low": 611,
      "cost_bbb_cen": 1830,
      "cost_bbb_high": 3049
    },
    {
      "asset_id": "ANTONOV_AN225_2022_02_27",
      "name_en": "Antonov An-225 Mriya — World's Largest Strategic Transport Aircraft",
      "name_uk": "Антонов Ан-225 «Мрія» — найбільший стратегічний транспортний літак світу",
      "lat": 50.5945,
      "lon": 30.1932,
      "oblast": "Kyiv",
      "sector": "transport_and_ports",
      "lifecycle": "assessed",
      "destruction_level": "destroyed",
      "rebuildability": "rebuildable",
      "re_damage_count": 0,
      "pending_methodology": false,
      "financing_class": "concessional_led",
      "cost_baseline_low": 291,
      "cost_baseline_cen": 610,
      "cost_baseline_high": 930,
      "cost_cc_low": 334,
      "cost_cc_cen": 748,
      "cost_cc_high": 1162,
      "cost_bbb_low": 378,
      "cost_bbb_cen": 933,
      "cost_bbb_high": 1488
    },
    {
      "asset_id": "AVDIIVKA_COKE_PLANT_2022_02_24",
      "name_en": "Avdiivka Coke Plant",
      "name_uk": "Авдіївський коксохімічний завод",
      "lat": 48.1394,
      "lon": 37.7487,
      "oblast": "Donetsk",
      "sector": "industrial_and_agricultural",
      "lifecycle": "in_pipeline",
      "destruction_level": "destroyed",
      "rebuildability": "occupied",
      "re_damage_count": 3,
      "pending_methodology": false,
      "financing_class": "private_anchored",
      "cost_baseline_low": 942,
      "cost_baseline_cen": 2074,
      "cost_baseline_high": 3206,
      "cost_cc_low": 1084,
      "cost_cc_cen": 2546,
      "cost_cc_high": 4008,
      "cost_bbb_low": 1225,
      "cost_bbb_cen": 3177,
      "cost_bbb_high": 5130
    },
    {
      "asset_id": "AVDIIVKA_RESIDENTIAL_2023_10_01",
      "name_en": "Avdiivka Town Residential — Donetsk Oblast",
      "name_uk": "Житловий фонд Авдіївки — Донецька область",
      "lat": 48.1366,
      "lon": 37.7575,
      "oblast": "Donetsk",
      "sector": "residential",
      "lifecycle": "documented",
      "destruction_level": "destroyed",
      "rebuildability": "recently_liberated",
      "re_damage_count": 2,
      "pending_methodology": false,
      "financing_class": "concessional_led",
      "cost_baseline_low": 184,
      "cost_baseline_cen": 339,
      "cost_baseline_high": 493,
      "cost_cc_low": 211,
      "cost_cc_cen": 414,
      "cost_cc_high": 617,
      "cost_bbb_low": 239,
      "cost_bbb_cen": 515,
      "cost_bbb_high": 790
    },
    {
      "asset_id": "AZOVSTAL_STEEL_2022_03_01",
      "name_en": "Azovstal Iron and Steel Works, Mariupol",
      "name_uk": "Металургійний комбінат «Азовсталь», Маріуполь",
      "lat": 47.0665,
      "lon": 37.6003,
      "oblast": "Donetsk",
      "sector": "industrial_and_agricultural",
      "lifecycle": "in_pipeline",
      "destruction_level": "destroyed",
      "rebuildability": "occupied",
      "re_damage_count": 0,
      "pending_methodology": false,
      "financing_class": "private_anchored",
      "cost_baseline_low": 3551,
      "cost_baseline_cen": 7439,
      "cost_baseline_high": 11326,
      "cost_cc_low": 4083,
      "cost_cc_cen": 9121,
      "cost_cc_high": 14158,
      "cost_bbb_low": 4616,
      "cost_bbb_cen": 11369,
      "cost_bbb_high": 18122
    },
    {
      "asset_id": "BAKHMUT_WATER_SANITATION_2022_08_01",
      "name_en": "Bakhmut City Water Supply and Wastewater System",
      "name_uk": "Система водопостачання та водовідведення міста Бахмут",
      "lat": 48.5953,
      "lon": 38.0037,
      "oblast": "Donetsk",
      "sector": "water_and_sanitation",
      "lifecycle": "in_pipeline",
      "destruction_level": "destroyed",
      "rebuildability": "occupied",
      "re_damage_count": 0,
      "pending_methodology": false,
      "financing_class": "concessional_led",
      "cost_baseline_low": 80,
      "cost_baseline_cen": 187,
      "cost_baseline_high": 295,
      "cost_cc_low": 92,
      "cost_cc_cen": 230,
      "cost_cc_high": 368,
      "cost_bbb_low": 104,
      "cost_bbb_cen": 288,
      "cost_bbb_high": 471
    },
    {
      "asset_id": "BORODYANKA_RESIDENTIAL_2022_03_27",
      "name_en": "Borodyanka Residential District",
      "name_uk": "Жилий масив Бородянка",
      "lat": 50.648,
      "lon": 29.931,
      "oblast": "Kyiv",
      "sector": "residential",
      "lifecycle": "under_reconstruction",
      "destruction_level": "destroyed",
      "rebuildability": "rebuildable",
      "re_damage_count": 0,
      "pending_methodology": false,
      "financing_class": "concessional_led",
      "cost_baseline_low": 93,
      "cost_baseline_cen": 166,
      "cost_baseline_high": 239,
      "cost_cc_low": 107,
      "cost_cc_cen": 203,
      "cost_cc_high": 299,
      "cost_bbb_low": 121,
      "cost_bbb_cen": 252,
      "cost_bbb_high": 383
    },
    {
      "asset_id": "BUCHA_RESIDENTIAL_2022_03_05",
      "name_en": "Bucha Residential District",
      "name_uk": "Жилий масив Буча",
      "lat": 50.5492,
      "lon": 30.2245,
      "oblast": "Kyiv",
      "sector": "residential",
      "lifecycle": "under_reconstruction",
      "destruction_level": "severe",
      "rebuildability": "rebuildable",
      "re_damage_count": 0,
      "pending_methodology": false,
      "financing_class": "concessional_led",
      "cost_baseline_low": 172,
      "cost_baseline_cen": 355,
      "cost_baseline_high": 539,
      "cost_cc_low": 198,
      "cost_cc_cen": 436,
      "cost_cc_high": 674,
      "cost_bbb_low": 224,
      "cost_bbb_cen": 543,
      "cost_bbb_high": 862
    },
    {
      "asset_id": "CHASIV_YAR_DISTRICT_HOSPITAL_2023_07_09",
      "name_en": "Chasiv Yar District Hospital",
      "name_uk": "Часів-Ярська районна лікарня",
      "lat": 48.5999,
      "lon": 37.8524,
      "oblast": "Donetsk",
      "sector": "healthcare",
      "lifecycle": "documented",
      "destruction_level": "destroyed",
      "rebuildability": "frontline_adjacent",
      "re_damage_count": 3,
      "pending_methodology": false,
      "financing_class": "concessional_led",
      "cost_baseline_low": 14,
      "cost_baseline_cen": 25,
      "cost_baseline_high": 36,
      "cost_cc_low": 16,
      "cost_cc_cen": 31,
      "cost_cc_high": 45,
      "cost_bbb_low": 18,
      "cost_bbb_cen": 38,
      "cost_bbb_high": 58
    },
    {
      "asset_id": "CHASIV_YAR_RESIDENTIAL_2023_07_01",
      "name_en": "Chasiv Yar Residential Blocks",
      "name_uk": "Часів Яр — житлові квартали міста",
      "lat": 48.6008,
      "lon": 37.8412,
      "oblast": "Donetsk",
      "sector": "residential",
      "lifecycle": "documented",
      "destruction_level": "destroyed",
      "rebuildability": "frontline_adjacent",
      "re_damage_count": 4,
      "pending_methodology": false,
      "financing_class": "blended",
      "cost_baseline_low": 168,
      "cost_baseline_cen": 330,
      "cost_baseline_high": 492,
      "cost_cc_low": 193,
      "cost_cc_cen": 403,
      "cost_cc_high": 615,
      "cost_bbb_low": 218,
      "cost_bbb_cen": 495,
      "cost_bbb_high": 772
    },
    {
      "asset_id": "CHERNIHIV_NORTH_RESIDENTIAL_2022_03_09",
      "name_en": "Chernihiv North Residential District",
      "name_uk": "Північний житловий масив, Чернігів",
      "lat": 51.513,
      "lon": 31.28,
      "oblast": "Chernihiv",
      "sector": "residential",
      "lifecycle": "assessed",
      "destruction_level": "severe",
      "rebuildability": "rebuildable",
      "re_damage_count": 0,
      "pending_methodology": false,
      "financing_class": "concessional_led",
      "cost_baseline_low": 228,
      "cost_baseline_cen": 484,
      "cost_baseline_high": 739,
      "cost_cc_low": 262,
      "cost_cc_cen": 593,
      "cost_cc_high": 924,
      "cost_bbb_low": 297,
      "cost_bbb_cen": 740,
      "cost_bbb_high": 1182
    },
    {
      "asset_id": "CHERNIHIV_POWER_SUBSTATION_2022_03_03",
      "name_en": "Chernihiv Oblast 330kV Transmission Substation",
      "name_uk": "Підстанція 330 кВ Чернігівської області",
      "lat": 51.5021,
      "lon": 31.2885,
      "oblast": "Chernihiv",
      "sector": "energy_and_power",
      "lifecycle": "assessed",
      "destruction_level": "moderate",
      "rebuildability": "rebuildable",
      "re_damage_count": 0,
      "pending_methodology": false,
      "financing_class": "concessional_led",
      "cost_baseline_low": 6,
      "cost_baseline_cen": 18,
      "cost_baseline_high": 30,
      "cost_cc_low": 7,
      "cost_cc_cen": 23,
      "cost_cc_high": 38,
      "cost_bbb_low": 8,
      "cost_bbb_cen": 29,
      "cost_bbb_high": 49
    },
    {
      "asset_id": "CHERNIHIV_REGIONAL_LIBRARY_2022_03_03",
      "name_en": "Chernihiv Regional Universal Scientific Library",
      "name_uk": "Чернігівська обласна універсальна наукова бібліотека",
      "lat": 51.4982,
      "lon": 31.2893,
      "oblast": "Chernihiv",
      "sector": "public_administration",
      "lifecycle": "funded",
      "destruction_level": "severe",
      "rebuildability": "rebuildable",
      "re_damage_count": 0,
      "pending_methodology": false,
      "financing_class": "grant_led",
      "cost_baseline_low": 7,
      "cost_baseline_cen": 16,
      "cost_baseline_high": 24,
      "cost_cc_low": 8,
      "cost_cc_cen": 19,
      "cost_cc_high": 30,
      "cost_bbb_low": 9,
      "cost_bbb_cen": 24,
      "cost_bbb_high": 39
    },
    {
      "asset_id": "CHERNIHIV_RESIDENTIAL_2022_03_10",
      "name_en": "Chernihiv Multi-District Residential Damage",
      "name_uk": "Багатоквартальні житлові пошкодження Чернігова",
      "lat": 51.4939,
      "lon": 31.2947,
      "oblast": "Chernihiv",
      "sector": "residential",
      "lifecycle": "assessed",
      "destruction_level": "moderate",
      "rebuildability": "rebuildable",
      "re_damage_count": 0,
      "pending_methodology": false,
      "financing_class": "concessional_led",
      "cost_baseline_low": 111,
      "cost_baseline_cen": 289,
      "cost_baseline_high": 467,
      "cost_cc_low": 128,
      "cost_cc_cen": 356,
      "cost_cc_high": 583,
      "cost_bbb_low": 145,
      "cost_bbb_cen": 446,
      "cost_bbb_high": 747
    },
    {
      "asset_id": "CHERNIHIV_SCHOOL_18_2022_03_03",
      "name_en": "Chernihiv Secondary School No. 18",
      "name_uk": "Чернігівська загальноосвітня школа №18",
      "lat": 51.4975,
      "lon": 31.287,
      "oblast": "Chernihiv",
      "sector": "education",
      "lifecycle": "assessed",
      "destruction_level": "severe",
      "rebuildability": "rebuildable",
      "re_damage_count": 0,
      "pending_methodology": false,
      "financing_class": "concessional_led",
      "cost_baseline_low": 4,
      "cost_baseline_cen": 9,
      "cost_baseline_high": 14,
      "cost_cc_low": 5,
      "cost_cc_cen": 11,
      "cost_cc_high": 17,
      "cost_bbb_low": 5,
      "cost_bbb_cen": 14,
      "cost_bbb_high": 22
    },
    {
      "asset_id": "DNIPRO_AMUR_NIZHNODNIPROVSKYI_BRIDGE_2024_07_08",
      "name_en": "Dnipro Amur-Nizhnodniprovskyi Road Bridge",
      "name_uk": "Амурсько-Нижньодніпровський міст у Дніпрі",
      "lat": 48.4195,
      "lon": 35.0468,
      "oblast": "Dnipropetrovsk",
      "sector": "transport_and_ports",
      "lifecycle": "assessed",
      "destruction_level": "moderate",
      "rebuildability": "rebuildable",
      "re_damage_count": 0,
      "pending_methodology": false,
      "financing_class": "concessional_led",
      "cost_baseline_low": 42,
      "cost_baseline_cen": 72,
      "cost_baseline_high": 102,
      "cost_cc_low": 48,
      "cost_cc_cen": 88,
      "cost_cc_high": 128,
      "cost_bbb_low": 54,
      "cost_bbb_cen": 108,
      "cost_bbb_high": 162
    },
    {
      "asset_id": "DNIPRO_OKHMATDYT_CHILDREN_2024_04_08",
      "name_en": "Dnipro Children's Regional Clinical Hospital",
      "name_uk": "Дніпропетровська обласна дитяча клінічна лікарня",
      "lat": 48.478,
      "lon": 35.062,
      "oblast": "Dnipropetrovsk",
      "sector": "healthcare",
      "lifecycle": "assessed",
      "destruction_level": "moderate",
      "rebuildability": "rebuildable",
      "re_damage_count": 1,
      "pending_methodology": false,
      "financing_class": "concessional_led",
      "cost_baseline_low": 25,
      "cost_baseline_cen": 52,
      "cost_baseline_high": 79,
      "cost_cc_low": 29,
      "cost_cc_cen": 64,
      "cost_cc_high": 99,
      "cost_bbb_low": 32,
      "cost_bbb_cen": 80,
      "cost_bbb_high": 127
    },
    {
      "asset_id": "DNIPRO_RESIDENTIAL_2023_01_14",
      "name_en": "Dnipro Residential Apartment Block — Chechelivskiy District (January 2023 Missile Strike)",
      "name_uk": "Житловий будинок у Чечелівському районі Дніпра (ракетний удар, січень 2023)",
      "lat": 48.4647,
      "lon": 35.0462,
      "oblast": "Dnipropetrovsk",
      "sector": "residential",
      "lifecycle": "assessed",
      "destruction_level": "severe",
      "rebuildability": "rebuildable",
      "re_damage_count": 0,
      "pending_methodology": false,
      "financing_class": "concessional_led",
      "cost_baseline_low": 22,
      "cost_baseline_cen": 45,
      "cost_baseline_high": 68,
      "cost_cc_low": 25,
      "cost_cc_cen": 55,
      "cost_cc_high": 85,
      "cost_bbb_low": 28,
      "cost_bbb_cen": 68,
      "cost_bbb_high": 108
    },
    {
      "asset_id": "HOSTOMEL_AIRPORT_2022_02_24",
      "name_en": "Antonov Airport (Hostomel), Kyiv Oblast",
      "name_uk": "Аеропорт Антонов, Гостомель",
      "lat": 50.5945,
      "lon": 30.1932,
      "oblast": "Kyiv",
      "sector": "transport_and_ports",
      "lifecycle": "assessed",
      "destruction_level": "destroyed",
      "rebuildability": "rebuildable",
      "re_damage_count": 0,
      "pending_methodology": false,
      "financing_class": "concessional_led",
      "cost_baseline_low": 17,
      "cost_baseline_cen": 35,
      "cost_baseline_high": 53,
      "cost_cc_low": 19,
      "cost_cc_cen": 43,
      "cost_cc_high": 66,
      "cost_bbb_low": 22,
      "cost_bbb_cen": 53,
      "cost_bbb_high": 85
    },
    {
      "asset_id": "ILLICH_STEEL_MARIUPOL_2022_03_01",
      "name_en": "Illich Iron and Steel Works (Ilyich), Mariupol",
      "name_uk": "Металургійний комбінат імені Ілліча, Маріуполь",
      "lat": 47.1023,
      "lon": 37.5601,
      "oblast": "Donetsk",
      "sector": "industrial_and_agricultural",
      "lifecycle": "in_pipeline",
      "destruction_level": "destroyed",
      "rebuildability": "occupied",
      "re_damage_count": 0,
      "pending_methodology": false,
      "financing_class": "private_anchored",
      "cost_baseline_low": 2294,
      "cost_baseline_cen": 4806,
      "cost_baseline_high": 7319,
      "cost_cc_low": 2638,
      "cost_cc_cen": 5893,
      "cost_cc_high": 9148,
      "cost_bbb_low": 2983,
      "cost_bbb_cen": 7346,
      "cost_bbb_high": 11710
    },
    {
      "asset_id": "INHULETS_MYKOLAIV_WATER_2022_03_01",
      "name_en": "Inhulets–Mykolaiv Water Supply System",
      "name_uk": "Інгулецька водопостачальна система Миколаєва",
      "lat": 46.965,
      "lon": 32,
      "oblast": "Mykolaiv",
      "sector": "water_and_sanitation",
      "lifecycle": "assessed",
      "destruction_level": "severe",
      "rebuildability": "recently_liberated",
      "re_damage_count": 2,
      "pending_methodology": false,
      "financing_class": "concessional_led",
      "cost_baseline_low": 194,
      "cost_baseline_cen": 527,
      "cost_baseline_high": 860,
      "cost_cc_low": 223,
      "cost_cc_cen": 649,
      "cost_cc_high": 1075,
      "cost_bbb_low": 253,
      "cost_bbb_cen": 814,
      "cost_bbb_high": 1376
    },
    {
      "asset_id": "IRPIN_RESIDENTIAL_2022_02_27",
      "name_en": "Irpin Residential District",
      "name_uk": "Жилий масив Ірпінь",
      "lat": 50.5218,
      "lon": 30.2499,
      "oblast": "Kyiv",
      "sector": "residential",
      "lifecycle": "under_reconstruction",
      "destruction_level": "severe",
      "rebuildability": "rebuildable",
      "re_damage_count": 0,
      "pending_methodology": false,
      "financing_class": "concessional_led",
      "cost_baseline_low": 138,
      "cost_baseline_cen": 284,
      "cost_baseline_high": 431,
      "cost_cc_low": 158,
      "cost_cc_cen": 349,
      "cost_cc_high": 539,
      "cost_bbb_low": 179,
      "cost_bbb_cen": 434,
      "cost_bbb_high": 690
    },
    {
      "asset_id": "IZMAIL_GRAIN_TERMINAL_2023_07_26",
      "name_en": "Izmail Danube Grain Terminal (July 2023 Drone Strike)",
      "name_uk": "Ізмаїльський зерновий термінал на Дунаї (атака дронів, липень 2023)",
      "lat": 45.3447,
      "lon": 28.8459,
      "oblast": "Odesa",
      "sector": "industrial_and_agricultural",
      "lifecycle": "assessed",
      "destruction_level": "moderate",
      "rebuildability": "rebuildable",
      "re_damage_count": 2,
      "pending_methodology": false,
      "financing_class": "private_anchored",
      "cost_baseline_low": 8,
      "cost_baseline_cen": 25,
      "cost_baseline_high": 41,
      "cost_cc_low": 9,
      "cost_cc_cen": 31,
      "cost_cc_high": 52,
      "cost_bbb_low": 10,
      "cost_bbb_cen": 38,
      "cost_bbb_high": 66
    },
    {
      "asset_id": "IZMAIL_SUVOROV_MUSEUM_2024_07_14",
      "name_en": "Izmail Suvorov Museum of History and Military Glory",
      "name_uk": "Ізмаїльський музей імені О.В.Суворова — Музей Ізмаїльської фортеці",
      "lat": 45.35,
      "lon": 28.842,
      "oblast": "Odesa",
      "sector": "heritage_and_culture",
      "lifecycle": "assessed",
      "destruction_level": "moderate",
      "rebuildability": "rebuildable",
      "re_damage_count": 0,
      "pending_methodology": false,
      "financing_class": "grant_led",
      "cost_baseline_low": 5,
      "cost_baseline_cen": 9,
      "cost_baseline_high": 13,
      "cost_cc_low": 6,
      "cost_cc_cen": 11,
      "cost_cc_high": 16,
      "cost_bbb_low": 8,
      "cost_bbb_cen": 15,
      "cost_bbb_high": 22
    },
    {
      "asset_id": "IZYUM_DISTRICT_HOSPITAL_2022_04_01",
      "name_en": "Izyum District Central Hospital",
      "name_uk": "Ізюмська центральна районна лікарня",
      "lat": 49.201,
      "lon": 37.278,
      "oblast": "Kharkiv",
      "sector": "healthcare",
      "lifecycle": "assessed",
      "destruction_level": "severe",
      "rebuildability": "recently_liberated",
      "re_damage_count": 0,
      "pending_methodology": false,
      "financing_class": "concessional_led",
      "cost_baseline_low": 17,
      "cost_baseline_cen": 37,
      "cost_baseline_high": 56,
      "cost_cc_low": 19,
      "cost_cc_cen": 45,
      "cost_cc_high": 70,
      "cost_bbb_low": 22,
      "cost_bbb_cen": 56,
      "cost_bbb_high": 90
    },
    {
      "asset_id": "KAKHOVKA_HPP_2023_06_06",
      "name_en": "Kakhovka Hydroelectric Power Plant and Dam",
      "name_uk": "Каховська гідроелектростанція та гребля",
      "lat": 46.7667,
      "lon": 33.3833,
      "oblast": "Kherson",
      "sector": "energy_and_power",
      "lifecycle": "assessed",
      "destruction_level": "destroyed",
      "rebuildability": "occupied",
      "re_damage_count": 0,
      "pending_methodology": false,
      "financing_class": "concessional_led",
      "cost_baseline_low": 525,
      "cost_baseline_cen": 1032,
      "cost_baseline_high": 1538,
      "cost_cc_low": 604,
      "cost_cc_cen": 1263,
      "cost_cc_high": 1922,
      "cost_bbb_low": 683,
      "cost_bbb_cen": 1572,
      "cost_bbb_high": 2461
    },
    {
      "asset_id": "KARAZIN_KHARKIV_UNIVERSITY_2022_03_01",
      "name_en": "V.N. Karazin Kharkiv National University",
      "name_uk": "Харківський національний університет ім. В.Н. Каразіна",
      "lat": 50.0021,
      "lon": 36.229,
      "oblast": "Kharkiv",
      "sector": "education",
      "lifecycle": "assessed",
      "destruction_level": "moderate",
      "rebuildability": "rebuildable",
      "re_damage_count": 4,
      "pending_methodology": false,
      "financing_class": "concessional_led",
      "cost_baseline_low": 86,
      "cost_baseline_cen": 211,
      "cost_baseline_high": 335,
      "cost_cc_low": 99,
      "cost_cc_cen": 259,
      "cost_cc_high": 419,
      "cost_bbb_low": 111,
      "cost_bbb_cen": 324,
      "cost_bbb_high": 537
    },
    {
      "asset_id": "KHARKIV_CHP_2022_03_24",
      "name_en": "Kharkiv CHP-5 Combined Heat and Power Station",
      "name_uk": "Харківська теплоелектроцентраль ТЕЦ-5",
      "lat": 49.995,
      "lon": 36.18,
      "oblast": "Kharkiv",
      "sector": "energy_and_power",
      "lifecycle": "assessed",
      "destruction_level": "severe",
      "rebuildability": "rebuildable",
      "re_damage_count": 4,
      "pending_methodology": false,
      "financing_class": "concessional_led",
      "cost_baseline_low": 171,
      "cost_baseline_cen": 360,
      "cost_baseline_high": 549,
      "cost_cc_low": 197,
      "cost_cc_cen": 442,
      "cost_cc_high": 686,
      "cost_bbb_low": 223,
      "cost_bbb_cen": 551,
      "cost_bbb_high": 878
    },
    {
      "asset_id": "KHARKIV_HISTORICAL_CENTRE_2022_03_01",
      "name_en": "Kharkiv Historical City Centre — Heritage Building Cluster",
      "name_uk": "Харків — кластер пам'яток архітектури історичного центру",
      "lat": 49.9946,
      "lon": 36.2313,
      "oblast": "Kharkiv",
      "sector": "heritage_and_culture",
      "lifecycle": "assessed",
      "destruction_level": "severe",
      "rebuildability": "rebuildable",
      "re_damage_count": 4,
      "pending_methodology": false,
      "financing_class": "grant_led",
      "cost_baseline_low": 184,
      "cost_baseline_cen": 346,
      "cost_baseline_high": 508,
      "cost_cc_low": 212,
      "cost_cc_cen": 415,
      "cost_cc_high": 635,
      "cost_bbb_low": 276,
      "cost_bbb_cen": 554,
      "cost_bbb_high": 914
    },
    {
      "asset_id": "KHARKIV_INDUSTRIAL_DISTRICT_RESIDENTIAL_2022_04_01",
      "name_en": "Kharkiv Industrialnyi District Residential Housing Stock",
      "name_uk": "Харків — житловий фонд Індустріального району",
      "lat": 49.9635,
      "lon": 36.2918,
      "oblast": "Kharkiv",
      "sector": "residential",
      "lifecycle": "assessed",
      "destruction_level": "severe",
      "rebuildability": "rebuildable",
      "re_damage_count": 3,
      "pending_methodology": false,
      "financing_class": "blended",
      "cost_baseline_low": 195,
      "cost_baseline_cen": 342,
      "cost_baseline_high": 490,
      "cost_cc_low": 224,
      "cost_cc_cen": 418,
      "cost_cc_high": 612,
      "cost_bbb_low": 253,
      "cost_bbb_cen": 513,
      "cost_bbb_high": 773
    },
    {
      "asset_id": "KHARKIV_METRO_2022_03_01",
      "name_en": "Kharkiv Metro System — Infrastructure Damage",
      "name_uk": "Харківський метрополітен — пошкодження",
      "lat": 49.9935,
      "lon": 36.2304,
      "oblast": "Kharkiv",
      "sector": "transport_and_ports",
      "lifecycle": "assessed",
      "destruction_level": "moderate",
      "rebuildability": "rebuildable",
      "re_damage_count": 5,
      "pending_methodology": false,
      "financing_class": "concessional_led",
      "cost_baseline_low": 23,
      "cost_baseline_cen": 106,
      "cost_baseline_high": 188,
      "cost_cc_low": 26,
      "cost_cc_cen": 131,
      "cost_cc_high": 236,
      "cost_bbb_low": 30,
      "cost_bbb_cen": 166,
      "cost_bbb_high": 302
    },
    {
      "asset_id": "KHARKIV_METRO_LINE1_2022_04_01",
      "name_en": "Kharkiv Metro Line 1 — Kholodna Hora to Rozkidna Infrastructure",
      "name_uk": "Харківський метрополітен, лінія 1 — Холодна Гора — Розкидна",
      "lat": 49.9925,
      "lon": 36.2311,
      "oblast": "Kharkiv",
      "sector": "transport_and_ports",
      "lifecycle": "under_reconstruction",
      "destruction_level": "moderate",
      "rebuildability": "rebuildable",
      "re_damage_count": 0,
      "pending_methodology": false,
      "financing_class": "concessional_led",
      "cost_baseline_low": 10,
      "cost_baseline_cen": 48,
      "cost_baseline_high": 85,
      "cost_cc_low": 12,
      "cost_cc_cen": 60,
      "cost_cc_high": 107,
      "cost_bbb_low": 13,
      "cost_bbb_cen": 75,
      "cost_bbb_high": 137
    },
    {
      "asset_id": "KHARKIV_NATIONAL_AEROSPACE_UNIVERSITY_2022_03_01",
      "name_en": "Kharkiv National Aerospace University — N. Ye. Zhukovsky National Aerospace University (KhAI)",
      "name_uk": "Харківський національний аерокосмічний університет ім. М.Є. Жуковського (ХАІ)",
      "lat": 49.9934,
      "lon": 36.2545,
      "oblast": "Kharkiv",
      "sector": "education",
      "lifecycle": "assessed",
      "destruction_level": "severe",
      "rebuildability": "rebuildable",
      "re_damage_count": 2,
      "pending_methodology": false,
      "financing_class": "grant_led",
      "cost_baseline_low": 68,
      "cost_baseline_cen": 120,
      "cost_baseline_high": 173,
      "cost_cc_low": 78,
      "cost_cc_cen": 146,
      "cost_cc_high": 216,
      "cost_bbb_low": 88,
      "cost_bbb_cen": 181,
      "cost_bbb_high": 274
    },
    {
      "asset_id": "KHARKIV_OBLAST_ADMIN_2022_03_01",
      "name_en": "Kharkiv Oblast State Administration Building",
      "name_uk": "Харківська обласна державна адміністрація",
      "lat": 49.9935,
      "lon": 36.2304,
      "oblast": "Kharkiv",
      "sector": "public_administration",
      "lifecycle": "funded",
      "destruction_level": "severe",
      "rebuildability": "rebuildable",
      "re_damage_count": 1,
      "pending_methodology": false,
      "financing_class": "grant_led",
      "cost_baseline_low": 40,
      "cost_baseline_cen": 84,
      "cost_baseline_high": 128,
      "cost_cc_low": 46,
      "cost_cc_cen": 103,
      "cost_cc_high": 160,
      "cost_bbb_low": 52,
      "cost_bbb_cen": 128,
      "cost_bbb_high": 205
    },
    {
      "asset_id": "KHARKIV_POLYTECHNIC_INSTITUTE_2022_02_28",
      "name_en": "National Technical University KhPI — Kharkiv Polytechnic Institute",
      "name_uk": "Національний технічний університет «ХПІ»",
      "lat": 49.9947,
      "lon": 36.2395,
      "oblast": "Kharkiv",
      "sector": "education",
      "lifecycle": "assessed",
      "destruction_level": "moderate",
      "rebuildability": "rebuildable",
      "re_damage_count": 6,
      "pending_methodology": false,
      "financing_class": "concessional_led",
      "cost_baseline_low": 143,
      "cost_baseline_cen": 351,
      "cost_baseline_high": 559,
      "cost_cc_low": 164,
      "cost_cc_cen": 432,
      "cost_cc_high": 699,
      "cost_bbb_low": 186,
      "cost_bbb_cen": 540,
      "cost_bbb_high": 895
    },
    {
      "asset_id": "KHARKIV_REGIONAL_CHILDRENS_HOSPITAL_2022_03_06",
      "name_en": "Kharkiv Regional Children's Clinical Hospital",
      "name_uk": "Харківська обласна дитяча клінічна лікарня",
      "lat": 49.9905,
      "lon": 36.2421,
      "oblast": "Kharkiv",
      "sector": "healthcare",
      "lifecycle": "assessed",
      "destruction_level": "moderate",
      "rebuildability": "rebuildable",
      "re_damage_count": 3,
      "pending_methodology": false,
      "financing_class": "concessional_led",
      "cost_baseline_low": 33,
      "cost_baseline_cen": 71,
      "cost_baseline_high": 109,
      "cost_cc_low": 38,
      "cost_cc_cen": 88,
      "cost_cc_high": 137,
      "cost_bbb_low": 43,
      "cost_bbb_cen": 109,
      "cost_bbb_high": 175
    },
    {
      "asset_id": "KHARKIV_REGIONAL_HOSPITAL_2022_03_01",
      "name_en": "Kharkiv Regional Clinical Hospital",
      "name_uk": "Харківська обласна клінічна лікарня",
      "lat": 49.9782,
      "lon": 36.2376,
      "oblast": "Kharkiv",
      "sector": "healthcare",
      "lifecycle": "assessed",
      "destruction_level": "moderate",
      "rebuildability": "rebuildable",
      "re_damage_count": 0,
      "pending_methodology": false,
      "financing_class": "concessional_led",
      "cost_baseline_low": 67,
      "cost_baseline_cen": 155,
      "cost_baseline_high": 242,
      "cost_cc_low": 77,
      "cost_cc_cen": 190,
      "cost_cc_high": 302,
      "cost_bbb_low": 87,
      "cost_bbb_cen": 237,
      "cost_bbb_high": 387
    },
    {
      "asset_id": "KHARKIV_SALTIVKA_PHASE2_2022_09_01",
      "name_en": "Kharkiv Saltivka-Adjacent Residential Districts — Pavlove Pole and Nemyshlya",
      "name_uk": "Прилеглі до Салтівки житлові масиви Харкова — Павлове Поле та Немишля",
      "lat": 49.9895,
      "lon": 36.2826,
      "oblast": "Kharkiv",
      "sector": "residential",
      "lifecycle": "assessed",
      "destruction_level": "moderate",
      "rebuildability": "rebuildable",
      "re_damage_count": 0,
      "pending_methodology": false,
      "financing_class": "concessional_led",
      "cost_baseline_low": 217,
      "cost_baseline_cen": 559,
      "cost_baseline_high": 900,
      "cost_cc_low": 250,
      "cost_cc_cen": 688,
      "cost_cc_high": 1125,
      "cost_bbb_low": 282,
      "cost_bbb_cen": 862,
      "cost_bbb_high": 1441
    },
    {
      "asset_id": "KHERSON_ANTONIVSKYI_RAILWAY_BRIDGE_2022_08_27",
      "name_en": "Antonivka Railway Bridge over the Dnipro (Kherson)",
      "name_uk": "Антонівський залізничний міст через Дніпро (Херсон)",
      "lat": 46.7438,
      "lon": 32.7834,
      "oblast": "Kherson",
      "sector": "transport_and_ports",
      "lifecycle": "assessed",
      "destruction_level": "destroyed",
      "rebuildability": "rebuildable",
      "re_damage_count": 0,
      "pending_methodology": false,
      "financing_class": "concessional_led",
      "cost_baseline_low": 68,
      "cost_baseline_cen": 121,
      "cost_baseline_high": 174,
      "cost_cc_low": 78,
      "cost_cc_cen": 148,
      "cost_cc_high": 217,
      "cost_bbb_low": 88,
      "cost_bbb_cen": 181,
      "cost_bbb_high": 274
    },
    {
      "asset_id": "KHERSON_CENTRAL_RESIDENTIAL_2022_11_11",
      "name_en": "Kherson City Central Residential Districts (post-liberation)",
      "name_uk": "Центральні житлові райони Херсона (після деокупації)",
      "lat": 46.6354,
      "lon": 32.6169,
      "oblast": "Kherson",
      "sector": "residential",
      "lifecycle": "assessed",
      "destruction_level": "severe",
      "rebuildability": "rebuildable",
      "re_damage_count": 3,
      "pending_methodology": false,
      "financing_class": "concessional_led",
      "cost_baseline_low": 385,
      "cost_baseline_cen": 829,
      "cost_baseline_high": 1273,
      "cost_cc_low": 443,
      "cost_cc_cen": 1017,
      "cost_cc_high": 1591,
      "cost_bbb_low": 501,
      "cost_bbb_cen": 1269,
      "cost_bbb_high": 2036
    },
    {
      "asset_id": "KHERSON_OLESHKY_WATER_PLANT_2022_11_01",
      "name_en": "Kherson City Water Treatment Plant (Post-Liberation Damage)",
      "name_uk": "Міська станція водопідготовки Херсона (пошкодження після деокупації)",
      "lat": 46.6249,
      "lon": 32.6147,
      "oblast": "Kherson",
      "sector": "water_and_sanitation",
      "lifecycle": "assessed",
      "destruction_level": "moderate",
      "rebuildability": "rebuildable",
      "re_damage_count": 0,
      "pending_methodology": false,
      "financing_class": "concessional_led",
      "cost_baseline_low": 50,
      "cost_baseline_cen": 174,
      "cost_baseline_high": 298,
      "cost_cc_low": 57,
      "cost_cc_cen": 215,
      "cost_cc_high": 372,
      "cost_bbb_low": 65,
      "cost_bbb_cen": 271,
      "cost_bbb_high": 476
    },
    {
      "asset_id": "KHERSON_POST_KAKHOVKA_WATER_2023_06_06",
      "name_en": "Kherson City Water and Sanitation System (post-Kakhovka)",
      "name_uk": "Система водопостачання та водовідведення Херсона (після руйнування Каховської ГЕС)",
      "lat": 46.6354,
      "lon": 32.6169,
      "oblast": "Kherson",
      "sector": "water_and_sanitation",
      "lifecycle": "assessed",
      "destruction_level": "severe",
      "rebuildability": "frontline_adjacent",
      "re_damage_count": 0,
      "pending_methodology": false,
      "financing_class": "concessional_led",
      "cost_baseline_low": 192,
      "cost_baseline_cen": 533,
      "cost_baseline_high": 873,
      "cost_cc_low": 221,
      "cost_cc_cen": 656,
      "cost_cc_high": 1091,
      "cost_bbb_low": 250,
      "cost_bbb_cen": 823,
      "cost_bbb_high": 1397
    },
    {
      "asset_id": "KHERSON_REGIONAL_HOSPITAL_2022_11_11",
      "name_en": "Kherson Regional Clinical Hospital",
      "name_uk": "Херсонська обласна клінічна лікарня",
      "lat": 46.6464,
      "lon": 32.6251,
      "oblast": "Kherson",
      "sector": "healthcare",
      "lifecycle": "assessed",
      "destruction_level": "severe",
      "rebuildability": "frontline_adjacent",
      "re_damage_count": 5,
      "pending_methodology": false,
      "financing_class": "concessional_led",
      "cost_baseline_low": 89,
      "cost_baseline_cen": 162,
      "cost_baseline_high": 234,
      "cost_cc_low": 103,
      "cost_cc_cen": 198,
      "cost_cc_high": 293,
      "cost_bbb_low": 116,
      "cost_bbb_cen": 245,
      "cost_bbb_high": 374
    },
    {
      "asset_id": "KHERSON_SHIPYARD_2022_11_11",
      "name_en": "Kherson Shipyard (Khersonsky Sudnobudivny Zavod)",
      "name_uk": "Херсонський суднобудівний завод",
      "lat": 46.6303,
      "lon": 32.6249,
      "oblast": "Kherson",
      "sector": "industrial_and_agricultural",
      "lifecycle": "assessed",
      "destruction_level": "severe",
      "rebuildability": "rebuildable",
      "re_damage_count": 3,
      "pending_methodology": false,
      "financing_class": "private_anchored",
      "cost_baseline_low": 98,
      "cost_baseline_cen": 185,
      "cost_baseline_high": 272,
      "cost_cc_low": 113,
      "cost_cc_cen": 226,
      "cost_cc_high": 340,
      "cost_bbb_low": 127,
      "cost_bbb_cen": 278,
      "cost_bbb_high": 428
    },
    {
      "asset_id": "KHERSON_STATE_UNIVERSITY_2022_03_02",
      "name_en": "Kherson State University",
      "name_uk": "Херсонський державний університет",
      "lat": 46.6488,
      "lon": 32.6098,
      "oblast": "Kherson",
      "sector": "education",
      "lifecycle": "assessed",
      "destruction_level": "moderate",
      "rebuildability": "frontline_adjacent",
      "re_damage_count": 2,
      "pending_methodology": false,
      "financing_class": "concessional_led",
      "cost_baseline_low": 26,
      "cost_baseline_cen": 66,
      "cost_baseline_high": 105,
      "cost_cc_low": 30,
      "cost_cc_cen": 81,
      "cost_cc_high": 132,
      "cost_bbb_low": 34,
      "cost_bbb_cen": 101,
      "cost_bbb_high": 169
    },
    {
      "asset_id": "KRAMATORSK_RESIDENTIAL_2022_04_08",
      "name_en": "Kramatorsk Residential District — Station and Central Areas",
      "name_uk": "Житловий масив Краматорська — Вокзальний та Центральний райони",
      "lat": 48.7351,
      "lon": 37.5671,
      "oblast": "Donetsk",
      "sector": "residential",
      "lifecycle": "assessed",
      "destruction_level": "moderate",
      "rebuildability": "rebuildable",
      "re_damage_count": 0,
      "pending_methodology": false,
      "financing_class": "concessional_led",
      "cost_baseline_low": 103,
      "cost_baseline_cen": 272,
      "cost_baseline_high": 440,
      "cost_cc_low": 119,
      "cost_cc_cen": 335,
      "cost_cc_high": 550,
      "cost_bbb_low": 135,
      "cost_bbb_cen": 420,
      "cost_bbb_high": 704
    },
    {
      "asset_id": "KREMENCHUK_KREMEN_OIL_REFINERY_2022_06_27",
      "name_en": "Kremenchuk Kremenchutskyi Oil Refinery Complex",
      "name_uk": "Кременчуцький нафтопереробний завод",
      "lat": 49.0882,
      "lon": 33.4117,
      "oblast": "Poltava",
      "sector": "energy_and_power",
      "lifecycle": "assessed",
      "destruction_level": "severe",
      "rebuildability": "rebuildable",
      "re_damage_count": 2,
      "pending_methodology": false,
      "financing_class": "private_anchored",
      "cost_baseline_low": 780,
      "cost_baseline_cen": 1240,
      "cost_baseline_high": 1700,
      "cost_cc_low": 897,
      "cost_cc_cen": 1488,
      "cost_cc_high": 2125,
      "cost_bbb_low": 1014,
      "cost_bbb_cen": 1790,
      "cost_bbb_high": 2550
    },
    {
      "asset_id": "KREMENCHUK_STROYMASH_PLANT_2022_06_27",
      "name_en": "Kremenchuk Stroymash Engineering Plant",
      "name_uk": "Кременчуцький завод Stroymash (будівельного машинобудування)",
      "lat": 49.0701,
      "lon": 33.4089,
      "oblast": "Poltava",
      "sector": "industrial_and_agricultural",
      "lifecycle": "assessed",
      "destruction_level": "destroyed",
      "rebuildability": "rebuildable",
      "re_damage_count": 1,
      "pending_methodology": false,
      "financing_class": "private_anchored",
      "cost_baseline_low": 52,
      "cost_baseline_cen": 105,
      "cost_baseline_high": 158,
      "cost_cc_low": 60,
      "cost_cc_cen": 128,
      "cost_cc_high": 197,
      "cost_bbb_low": 68,
      "cost_bbb_cen": 157,
      "cost_bbb_high": 246
    },
    {
      "asset_id": "KRYVORIZKA_TPP_2022_10_18",
      "name_en": "Kryvorizka Thermal Power Plant",
      "name_uk": "Криворізька теплова електростанція",
      "lat": 47.91,
      "lon": 33.34,
      "oblast": "Dnipropetrovsk",
      "sector": "energy_and_power",
      "lifecycle": "assessed",
      "destruction_level": "severe",
      "rebuildability": "rebuildable",
      "re_damage_count": 3,
      "pending_methodology": false,
      "financing_class": "concessional_led",
      "cost_baseline_low": 778,
      "cost_baseline_cen": 1602,
      "cost_baseline_high": 2426,
      "cost_cc_low": 895,
      "cost_cc_cen": 1964,
      "cost_cc_high": 3032,
      "cost_bbb_low": 1012,
      "cost_bbb_cen": 2447,
      "cost_bbb_high": 3881
    },
    {
      "asset_id": "KUINDZHI_MUSEUM_MARIUPOL_2022_03_25",
      "name_en": "Arkhip Kuindzhi Art Museum, Mariupol",
      "name_uk": "Маріупольський художній музей ім. А.І. Куїнджі",
      "lat": 47.099,
      "lon": 37.547,
      "oblast": "Donetsk",
      "sector": "heritage_and_culture",
      "lifecycle": "documented",
      "destruction_level": "destroyed",
      "rebuildability": "occupied",
      "re_damage_count": 0,
      "pending_methodology": false,
      "financing_class": "concessional_led",
      "cost_baseline_low": 26,
      "cost_baseline_cen": 75,
      "cost_baseline_high": 124,
      "cost_cc_low": 29,
      "cost_cc_cen": 93,
      "cost_cc_high": 156,
      "cost_bbb_low": 33,
      "cost_bbb_cen": 116,
      "cost_bbb_high": 199
    },
    {
      "asset_id": "KUPYANSK_RESIDENTIAL_2022_02_28",
      "name_en": "Kupyansk Residential District",
      "name_uk": "Жилий масив Куп'янськ",
      "lat": 49.7098,
      "lon": 37.5998,
      "oblast": "Kharkiv",
      "sector": "residential",
      "lifecycle": "assessed",
      "destruction_level": "severe",
      "rebuildability": "frontline_adjacent",
      "re_damage_count": 2,
      "pending_methodology": false,
      "financing_class": "concessional_led",
      "cost_baseline_low": 107,
      "cost_baseline_cen": 225,
      "cost_baseline_high": 343,
      "cost_cc_low": 123,
      "cost_cc_cen": 276,
      "cost_cc_high": 429,
      "cost_bbb_low": 139,
      "cost_bbb_cen": 344,
      "cost_bbb_high": 549
    },
    {
      "asset_id": "KUPYANSK_SCHOOL_COMPLEX_2022_09_10",
      "name_en": "Kupyansk Secondary School Complex",
      "name_uk": "Школи м. Куп'янськ — зведений комплекс",
      "lat": 49.7098,
      "lon": 37.5998,
      "oblast": "Kharkiv",
      "sector": "education",
      "lifecycle": "assessed",
      "destruction_level": "severe",
      "rebuildability": "frontline_adjacent",
      "re_damage_count": 1,
      "pending_methodology": false,
      "financing_class": "concessional_led",
      "cost_baseline_low": 11,
      "cost_baseline_cen": 24,
      "cost_baseline_high": 37,
      "cost_cc_low": 13,
      "cost_cc_cen": 29,
      "cost_cc_high": 46,
      "cost_bbb_low": 15,
      "cost_bbb_cen": 37,
      "cost_bbb_high": 59
    },
    {
      "asset_id": "LADYZHYNSKA_TPP_2024_04_11",
      "name_en": "Ladyzhynska Thermal Power Plant",
      "name_uk": "Ладижинська теплова електростанція",
      "lat": 48.68,
      "lon": 29.24,
      "oblast": "Vinnytsia",
      "sector": "energy_and_power",
      "lifecycle": "assessed",
      "destruction_level": "destroyed",
      "rebuildability": "rebuildable",
      "re_damage_count": 0,
      "pending_methodology": false,
      "financing_class": "concessional_led",
      "cost_baseline_low": 747,
      "cost_baseline_cen": 1330,
      "cost_baseline_high": 1913,
      "cost_cc_low": 859,
      "cost_cc_cen": 1625,
      "cost_cc_high": 2391,
      "cost_bbb_low": 971,
      "cost_bbb_cen": 2016,
      "cost_bbb_high": 3060
    },
    {
      "asset_id": "LYMAN_DISTRICT_HOSPITAL_2022_05_20",
      "name_en": "Lyman District Central Hospital",
      "name_uk": "Лиманська районна центральна лікарня",
      "lat": 48.9801,
      "lon": 37.8107,
      "oblast": "Donetsk",
      "sector": "healthcare",
      "lifecycle": "documented",
      "destruction_level": "destroyed",
      "rebuildability": "recently_liberated",
      "re_damage_count": 2,
      "pending_methodology": false,
      "financing_class": "concessional_led",
      "cost_baseline_low": 18,
      "cost_baseline_cen": 34,
      "cost_baseline_high": 50,
      "cost_cc_low": 21,
      "cost_cc_cen": 41,
      "cost_cc_high": 63,
      "cost_bbb_low": 24,
      "cost_bbb_cen": 51,
      "cost_bbb_high": 78
    },
    {
      "asset_id": "LYMAN_RESIDENTIAL_2022_05_20",
      "name_en": "Lyman Town Residential — Donetsk Oblast",
      "name_uk": "Житловий фонд Лимана — Донецька область",
      "lat": 48.9803,
      "lon": 37.8131,
      "oblast": "Donetsk",
      "sector": "residential",
      "lifecycle": "assessed",
      "destruction_level": "severe",
      "rebuildability": "recently_liberated",
      "re_damage_count": 1,
      "pending_methodology": false,
      "financing_class": "concessional_led",
      "cost_baseline_low": 136,
      "cost_baseline_cen": 291,
      "cost_baseline_high": 446,
      "cost_cc_low": 156,
      "cost_cc_cen": 357,
      "cost_cc_high": 558,
      "cost_bbb_low": 177,
      "cost_bbb_cen": 446,
      "cost_bbb_high": 714
    },
    {
      "asset_id": "LYMAN_RESIDENTIAL_DISTRICT_2022_05_20",
      "name_en": "Lyman Residential District Housing Stock",
      "name_uk": "Лиман — житловий фонд міста",
      "lat": 48.9782,
      "lon": 37.8133,
      "oblast": "Donetsk",
      "sector": "residential",
      "lifecycle": "assessed",
      "destruction_level": "severe",
      "rebuildability": "recently_liberated",
      "re_damage_count": 2,
      "pending_methodology": false,
      "financing_class": "blended",
      "cost_baseline_low": 72,
      "cost_baseline_cen": 126,
      "cost_baseline_high": 180,
      "cost_cc_low": 83,
      "cost_cc_cen": 154,
      "cost_cc_high": 225,
      "cost_bbb_low": 94,
      "cost_bbb_cen": 189,
      "cost_bbb_high": 284
    },
    {
      "asset_id": "LYMAN_WATER_TREATMENT_2022_05_01",
      "name_en": "Lyman Water Treatment Plant",
      "name_uk": "Лиманська станція водопідготовки",
      "lat": 48.9735,
      "lon": 37.8023,
      "oblast": "Donetsk",
      "sector": "water_and_sanitation",
      "lifecycle": "documented",
      "destruction_level": "destroyed",
      "rebuildability": "recently_liberated",
      "re_damage_count": 2,
      "pending_methodology": false,
      "financing_class": "grant_led",
      "cost_baseline_low": 14,
      "cost_baseline_cen": 25,
      "cost_baseline_high": 36,
      "cost_cc_low": 16,
      "cost_cc_cen": 31,
      "cost_cc_high": 45,
      "cost_bbb_low": 18,
      "cost_bbb_cen": 38,
      "cost_bbb_high": 58
    },
    {
      "asset_id": "MARIUPOL_DRAMA_THEATRE_2022_03_16",
      "name_en": "Mariupol Drama Theatre",
      "name_uk": "Маріупольський драматичний театр",
      "lat": 47.0975,
      "lon": 37.5449,
      "oblast": "Donetsk",
      "sector": "heritage_and_culture",
      "lifecycle": "assessed",
      "destruction_level": "destroyed",
      "rebuildability": "occupied",
      "re_damage_count": 0,
      "pending_methodology": false,
      "financing_class": "concessional_led",
      "cost_baseline_low": 55,
      "cost_baseline_cen": 151,
      "cost_baseline_high": 248,
      "cost_cc_low": 64,
      "cost_cc_cen": 187,
      "cost_cc_high": 310,
      "cost_bbb_low": 72,
      "cost_bbb_cen": 234,
      "cost_bbb_high": 396
    },
    {
      "asset_id": "MARIUPOL_LIVOBEREZHNYI_RESIDENTIAL_2022_03_01",
      "name_en": "Mariupol Livoberezhnyi (East Bank) Residential District",
      "name_uk": "Лівобережний житловий масив, Маріуполь",
      "lat": 47.072,
      "lon": 37.59,
      "oblast": "Donetsk",
      "sector": "residential",
      "lifecycle": "documented",
      "destruction_level": "destroyed",
      "rebuildability": "occupied",
      "re_damage_count": 0,
      "pending_methodology": false,
      "financing_class": "concessional_led",
      "cost_baseline_low": 3117,
      "cost_baseline_cen": 5745,
      "cost_baseline_high": 8374,
      "cost_cc_low": 3585,
      "cost_cc_cen": 7026,
      "cost_cc_high": 10467,
      "cost_bbb_low": 4052,
      "cost_bbb_cen": 8725,
      "cost_bbb_high": 13398
    },
    {
      "asset_id": "MARIUPOL_LIVYI_BEREG_RESIDENTIAL_2022_03_01",
      "name_en": "Mariupol Left Bank (Livyi Bereh) Large-Panel Residential District",
      "name_uk": "Маріуполь — житловий масив Лівий берег",
      "lat": 47.0762,
      "lon": 37.598,
      "oblast": "Donetsk",
      "sector": "residential",
      "lifecycle": "documented",
      "destruction_level": "destroyed",
      "rebuildability": "occupied",
      "re_damage_count": 0,
      "pending_methodology": false,
      "financing_class": "blended",
      "cost_baseline_low": 496,
      "cost_baseline_cen": 868,
      "cost_baseline_high": 1240,
      "cost_cc_low": 570,
      "cost_cc_cen": 1060,
      "cost_cc_high": 1550,
      "cost_bbb_low": 645,
      "cost_bbb_cen": 1300,
      "cost_bbb_high": 1955
    },
    {
      "asset_id": "MARIUPOL_MATERNITY_HOSPITAL_3_2022_03_09",
      "name_en": "Mariupol City Maternity Hospital No. 3",
      "name_uk": "Маріупольський міський пологовий будинок №3",
      "lat": 47.0942,
      "lon": 37.5516,
      "oblast": "Donetsk",
      "sector": "healthcare",
      "lifecycle": "documented",
      "destruction_level": "destroyed",
      "rebuildability": "occupied",
      "re_damage_count": 0,
      "pending_methodology": false,
      "financing_class": "concessional_led",
      "cost_baseline_low": 28,
      "cost_baseline_cen": 45,
      "cost_baseline_high": 63,
      "cost_cc_low": 32,
      "cost_cc_cen": 55,
      "cost_cc_high": 79,
      "cost_bbb_low": 36,
      "cost_bbb_cen": 68,
      "cost_bbb_high": 100
    },
    {
      "asset_id": "MARIUPOL_PRIMORSKY_RESIDENTIAL_2022_03_01",
      "name_en": "Mariupol Primorsky and Zhovtnevy Districts Residential",
      "name_uk": "Житловий фонд Приморського та Жовтневого районів Маріуполя",
      "lat": 47.1005,
      "lon": 37.562,
      "oblast": "Donetsk",
      "sector": "residential",
      "lifecycle": "documented",
      "destruction_level": "destroyed",
      "rebuildability": "occupied",
      "re_damage_count": 0,
      "pending_methodology": false,
      "financing_class": "concessional_led",
      "cost_baseline_low": 2449,
      "cost_baseline_cen": 4514,
      "cost_baseline_high": 6579,
      "cost_cc_low": 2817,
      "cost_cc_cen": 5521,
      "cost_cc_high": 8224,
      "cost_bbb_low": 3184,
      "cost_bbb_cen": 6856,
      "cost_bbb_high": 10527
    },
    {
      "asset_id": "MARIUPOL_ROAD_NETWORK_2022_03_01",
      "name_en": "Mariupol Urban Road Network",
      "name_uk": "Маріуполь — міська вулично-дорожня мережа",
      "lat": 47.0951,
      "lon": 37.5407,
      "oblast": "Donetsk",
      "sector": "transport_and_ports",
      "lifecycle": "documented",
      "destruction_level": "severe",
      "rebuildability": "occupied",
      "re_damage_count": 0,
      "pending_methodology": false,
      "financing_class": "concessional_led",
      "cost_baseline_low": 195,
      "cost_baseline_cen": 342,
      "cost_baseline_high": 490,
      "cost_cc_low": 224,
      "cost_cc_cen": 418,
      "cost_cc_high": 612,
      "cost_bbb_low": 253,
      "cost_bbb_cen": 513,
      "cost_bbb_high": 773
    },
    {
      "asset_id": "MARIUPOL_SCHOOL_89_2022_03_01",
      "name_en": "Mariupol School No. 89",
      "name_uk": "Маріупольська школа №89",
      "lat": 47.1031,
      "lon": 37.5687,
      "oblast": "Donetsk",
      "sector": "education",
      "lifecycle": "documented",
      "destruction_level": "destroyed",
      "rebuildability": "occupied",
      "re_damage_count": 0,
      "pending_methodology": false,
      "financing_class": "grant_led",
      "cost_baseline_low": 6,
      "cost_baseline_cen": 11,
      "cost_baseline_high": 16,
      "cost_cc_low": 7,
      "cost_cc_cen": 13,
      "cost_cc_high": 20,
      "cost_bbb_low": 8,
      "cost_bbb_cen": 16,
      "cost_bbb_high": 24
    },
    {
      "asset_id": "MARIUPOL_SEA_PORT_2022_03_01",
      "name_en": "Mariupol Sea Trade Port",
      "name_uk": "Маріупольський морський торговельний порт",
      "lat": 47.066,
      "lon": 37.575,
      "oblast": "Donetsk",
      "sector": "transport_and_ports",
      "lifecycle": "documented",
      "destruction_level": "destroyed",
      "rebuildability": "occupied",
      "re_damage_count": 0,
      "pending_methodology": false,
      "financing_class": "concessional_led",
      "cost_baseline_low": 12,
      "cost_baseline_cen": 29,
      "cost_baseline_high": 46,
      "cost_cc_low": 14,
      "cost_cc_cen": 36,
      "cost_cc_high": 58,
      "cost_bbb_low": 16,
      "cost_bbb_cen": 45,
      "cost_bbb_high": 74
    },
    {
      "asset_id": "MARIUPOL_STATE_UNIVERSITY_2022_03_15",
      "name_en": "Pryazovskyi State Technical University, Mariupol",
      "name_uk": "Приазовський державний технічний університет, Маріуполь",
      "lat": 47.108,
      "lon": 37.549,
      "oblast": "Donetsk",
      "sector": "education",
      "lifecycle": "documented",
      "destruction_level": "destroyed",
      "rebuildability": "occupied",
      "re_damage_count": 0,
      "pending_methodology": false,
      "financing_class": "concessional_led",
      "cost_baseline_low": 227,
      "cost_baseline_cen": 402,
      "cost_baseline_high": 576,
      "cost_cc_low": 261,
      "cost_cc_cen": 491,
      "cost_cc_high": 720,
      "cost_bbb_low": 295,
      "cost_bbb_cen": 609,
      "cost_bbb_high": 922
    },
    {
      "asset_id": "MARIUPOL_TECHNICAL_UNIVERSITY_2022_03_01",
      "name_en": "Pryazovskyi State Technical University, Mariupol",
      "name_uk": "Приазовський державний технічний університет, Маріуполь",
      "lat": 47.0944,
      "lon": 37.5488,
      "oblast": "Donetsk",
      "sector": "education",
      "lifecycle": "documented",
      "destruction_level": "destroyed",
      "rebuildability": "occupied",
      "re_damage_count": 0,
      "pending_methodology": false,
      "financing_class": "concessional_led",
      "cost_baseline_low": 128,
      "cost_baseline_cen": 227,
      "cost_baseline_high": 325,
      "cost_cc_low": 147,
      "cost_cc_cen": 277,
      "cost_cc_high": 407,
      "cost_bbb_low": 167,
      "cost_bbb_cen": 344,
      "cost_bbb_high": 521
    },
    {
      "asset_id": "MARIUPOL_WATER_WASTEWATER_2022_03_01",
      "name_en": "Mariupol Water Supply and Wastewater Treatment System",
      "name_uk": "Система водопостачання та водовідведення Маріуполя",
      "lat": 47.0958,
      "lon": 37.5421,
      "oblast": "Donetsk",
      "sector": "water_and_sanitation",
      "lifecycle": "in_pipeline",
      "destruction_level": "destroyed",
      "rebuildability": "occupied",
      "re_damage_count": 0,
      "pending_methodology": false,
      "financing_class": "concessional_led",
      "cost_baseline_low": 470,
      "cost_baseline_cen": 1102,
      "cost_baseline_high": 1735,
      "cost_cc_low": 540,
      "cost_cc_cen": 1355,
      "cost_cc_high": 2169,
      "cost_bbb_low": 611,
      "cost_bbb_cen": 1694,
      "cost_bbb_high": 2776
    },
    {
      "asset_id": "MYKOLAIV_NORTH_RESIDENTIAL_2022_04_01",
      "name_en": "Mykolaiv Northern Residential Districts (Korabelny, Zavodskoy)",
      "name_uk": "Північні житлові райони Миколаєва (Корабельний, Заводський)",
      "lat": 46.9843,
      "lon": 31.9974,
      "oblast": "Mykolaiv",
      "sector": "residential",
      "lifecycle": "assessed",
      "destruction_level": "moderate",
      "rebuildability": "rebuildable",
      "re_damage_count": 0,
      "pending_methodology": false,
      "financing_class": "concessional_led",
      "cost_baseline_low": 137,
      "cost_baseline_cen": 353,
      "cost_baseline_high": 569,
      "cost_cc_low": 157,
      "cost_cc_cen": 435,
      "cost_cc_high": 712,
      "cost_bbb_low": 178,
      "cost_bbb_cen": 545,
      "cost_bbb_high": 911
    },
    {
      "asset_id": "MYKOLAIV_REGIONAL_HOSPITAL_2022_04_15",
      "name_en": "Mykolaiv Regional Clinical Hospital",
      "name_uk": "Миколаївська обласна клінічна лікарня",
      "lat": 46.9658,
      "lon": 31.9916,
      "oblast": "Mykolaiv",
      "sector": "healthcare",
      "lifecycle": "assessed",
      "destruction_level": "severe",
      "rebuildability": "rebuildable",
      "re_damage_count": 1,
      "pending_methodology": false,
      "financing_class": "concessional_led",
      "cost_baseline_low": 97,
      "cost_baseline_cen": 171,
      "cost_baseline_high": 245,
      "cost_cc_low": 112,
      "cost_cc_cen": 208,
      "cost_cc_high": 306,
      "cost_bbb_low": 126,
      "cost_bbb_cen": 257,
      "cost_bbb_high": 388
    },
    {
      "asset_id": "MYKOLAIV_RESIDENTIAL_2022_08_01",
      "name_en": "Mykolaiv Central Residential District",
      "name_uk": "Центральний житловий масив, Миколаїв",
      "lat": 46.975,
      "lon": 31.994,
      "oblast": "Mykolaiv",
      "sector": "residential",
      "lifecycle": "assessed",
      "destruction_level": "moderate",
      "rebuildability": "rebuildable",
      "re_damage_count": 6,
      "pending_methodology": false,
      "financing_class": "concessional_led",
      "cost_baseline_low": 185,
      "cost_baseline_cen": 478,
      "cost_baseline_high": 771,
      "cost_cc_low": 213,
      "cost_cc_cen": 588,
      "cost_cc_high": 964,
      "cost_bbb_low": 241,
      "cost_bbb_cen": 737,
      "cost_bbb_high": 1233
    },
    {
      "asset_id": "MYKOLAIV_SHIPYARDS_2022_03_01",
      "name_en": "Mykolaiv Shipbuilding Facilities — Black Sea Shipyard / NIBULON complex",
      "name_uk": "Чорноморський суднобудівний завод / комплекс НІБУЛОН, Миколаїв",
      "lat": 46.968,
      "lon": 32.038,
      "oblast": "Mykolaiv",
      "sector": "transport_and_ports",
      "lifecycle": "assessed",
      "destruction_level": "severe",
      "rebuildability": "rebuildable",
      "re_damage_count": 4,
      "pending_methodology": false,
      "financing_class": "concessional_led",
      "cost_baseline_low": 4,
      "cost_baseline_cen": 10,
      "cost_baseline_high": 17,
      "cost_cc_low": 4,
      "cost_cc_cen": 13,
      "cost_cc_high": 21,
      "cost_bbb_low": 5,
      "cost_bbb_cen": 16,
      "cost_bbb_high": 27
    },
    {
      "asset_id": "MYKOLAIV_WATER_SUPPLY_2022_03_01",
      "name_en": "Mykolaiv City Water Supply Infrastructure (Dnipro-Mykolaiv Canal System)",
      "name_uk": "Система водопостачання Миколаєва (Дніпро-Миколаївський канал)",
      "lat": 46.975,
      "lon": 31.9946,
      "oblast": "Mykolaiv",
      "sector": "water_and_sanitation",
      "lifecycle": "funded",
      "destruction_level": "moderate",
      "rebuildability": "rebuildable",
      "re_damage_count": 0,
      "pending_methodology": false,
      "financing_class": "concessional_led",
      "cost_baseline_low": 61,
      "cost_baseline_cen": 205,
      "cost_baseline_high": 348,
      "cost_cc_low": 70,
      "cost_cc_cen": 253,
      "cost_cc_high": 435,
      "cost_bbb_low": 79,
      "cost_bbb_cen": 318,
      "cost_bbb_high": 557
    },
    {
      "asset_id": "NIKOPOL_RESIDENTIAL_2022_08_01",
      "name_en": "Nikopol City Residential — Cross-River Shelling from Enerhodar",
      "name_uk": "Житловий фонд Нікополя — обстріли з боку Енергодара",
      "lat": 47.5746,
      "lon": 34.3979,
      "oblast": "Dnipropetrovsk",
      "sector": "residential",
      "lifecycle": "assessed",
      "destruction_level": "moderate",
      "rebuildability": "rebuildable",
      "re_damage_count": 5,
      "pending_methodology": false,
      "financing_class": "concessional_led",
      "cost_baseline_low": 72,
      "cost_baseline_cen": 182,
      "cost_baseline_high": 292,
      "cost_cc_low": 83,
      "cost_cc_cen": 224,
      "cost_cc_high": 365,
      "cost_bbb_low": 94,
      "cost_bbb_cen": 281,
      "cost_bbb_high": 468
    },
    {
      "asset_id": "ODESA_FINE_ARTS_MUSEUM_2023_07_23",
      "name_en": "Odesa Fine Arts Museum",
      "name_uk": "Одеський художній музей",
      "lat": 46.487,
      "lon": 30.734,
      "oblast": "Odesa",
      "sector": "heritage_and_culture",
      "lifecycle": "assessed",
      "destruction_level": "moderate",
      "rebuildability": "rebuildable",
      "re_damage_count": 1,
      "pending_methodology": false,
      "financing_class": "concessional_led",
      "cost_baseline_low": 16,
      "cost_baseline_cen": 68,
      "cost_baseline_high": 121,
      "cost_cc_low": 18,
      "cost_cc_cen": 84,
      "cost_cc_high": 151,
      "cost_bbb_low": 21,
      "cost_bbb_cen": 107,
      "cost_bbb_high": 193
    },
    {
      "asset_id": "ODESA_MYKOLAIV_GRAIN_TERMINALS_2022_04_01",
      "name_en": "Odesa and Mykolaiv Grain Export Terminals",
      "name_uk": "Зернові експортні термінали Одеси та Миколаєва",
      "lat": 46.4825,
      "lon": 30.7233,
      "oblast": "Odesa",
      "sector": "industrial_and_agricultural",
      "lifecycle": "assessed",
      "destruction_level": "moderate",
      "rebuildability": "rebuildable",
      "re_damage_count": 4,
      "pending_methodology": false,
      "financing_class": "private_anchored",
      "cost_baseline_low": 181,
      "cost_baseline_cen": 574,
      "cost_baseline_high": 967,
      "cost_cc_low": 208,
      "cost_cc_cen": 709,
      "cost_cc_high": 1209,
      "cost_bbb_low": 235,
      "cost_bbb_cen": 892,
      "cost_bbb_high": 1548
    },
    {
      "asset_id": "ODESA_RESIDENTIAL_2023_07_23",
      "name_en": "Odesa Historic Centre Residential — Transfiguration Cathedral Neighbourhood",
      "name_uk": "Житловий фонд Одеського історичного центру — квартал Спасо-Преображенського собору",
      "lat": 46.4825,
      "lon": 30.7233,
      "oblast": "Odesa",
      "sector": "residential",
      "lifecycle": "assessed",
      "destruction_level": "moderate",
      "rebuildability": "rebuildable",
      "re_damage_count": 0,
      "pending_methodology": false,
      "financing_class": "concessional_led",
      "cost_baseline_low": 10,
      "cost_baseline_cen": 26,
      "cost_baseline_high": 41,
      "cost_cc_low": 11,
      "cost_cc_cen": 32,
      "cost_cc_high": 52,
      "cost_bbb_low": 13,
      "cost_bbb_cen": 40,
      "cost_bbb_high": 66
    },
    {
      "asset_id": "ODESA_TRANSFIGURATION_CATHEDRAL_2023_07_23",
      "name_en": "Holy Transfiguration Cathedral, Odesa",
      "name_uk": "Собор Преображення Господнього, Одеса",
      "lat": 46.4878,
      "lon": 30.7346,
      "oblast": "Odesa",
      "sector": "heritage_and_culture",
      "lifecycle": "assessed",
      "destruction_level": "severe",
      "rebuildability": "rebuildable",
      "re_damage_count": 0,
      "pending_methodology": false,
      "financing_class": "concessional_led",
      "cost_baseline_low": 19,
      "cost_baseline_cen": 90,
      "cost_baseline_high": 162,
      "cost_cc_low": 21,
      "cost_cc_cen": 112,
      "cost_cc_high": 202,
      "cost_bbb_low": 24,
      "cost_bbb_cen": 142,
      "cost_bbb_high": 259
    },
    {
      "asset_id": "OKHMATDYT_2024_07_08",
      "name_en": "Okhmatdyt National Children's Hospital — Toxicology and Dialysis Block",
      "name_uk": "Національна дитяча спеціалізована лікарня «Охматдит» — токсикологічний та діалізний корпус",
      "lat": 50.4536,
      "lon": 30.4549,
      "oblast": "Kyiv City",
      "sector": "healthcare",
      "lifecycle": "assessed",
      "destruction_level": "severe",
      "rebuildability": "rebuildable",
      "re_damage_count": 0,
      "pending_methodology": false,
      "financing_class": "concessional_led",
      "cost_baseline_low": 33,
      "cost_baseline_cen": 57,
      "cost_baseline_high": 82,
      "cost_cc_low": 38,
      "cost_cc_cen": 70,
      "cost_cc_high": 102,
      "cost_bbb_low": 43,
      "cost_bbb_cen": 87,
      "cost_bbb_high": 131
    },
    {
      "asset_id": "ORIKHIV_RESIDENTIAL_2022_08_01",
      "name_en": "Orikhiv Town Residential — Near-Frontline Zaporizhzhia Oblast",
      "name_uk": "Житловий фонд Оріхова — прифронтова зона Запорізької області",
      "lat": 47.565,
      "lon": 35.7898,
      "oblast": "Zaporizhzhia",
      "sector": "residential",
      "lifecycle": "assessed",
      "destruction_level": "severe",
      "rebuildability": "frontline_adjacent",
      "re_damage_count": 4,
      "pending_methodology": false,
      "financing_class": "concessional_led",
      "cost_baseline_low": 59,
      "cost_baseline_cen": 127,
      "cost_baseline_high": 195,
      "cost_cc_low": 68,
      "cost_cc_cen": 156,
      "cost_cc_high": 244,
      "cost_bbb_low": 77,
      "cost_bbb_cen": 195,
      "cost_bbb_high": 312
    },
    {
      "asset_id": "PRYDNIPROVSKA_CHP_2024_03_22",
      "name_en": "Prydniprovska Combined Heat and Power Plant",
      "name_uk": "Придніпровська ТЕЦ",
      "lat": 48.4351,
      "lon": 34.9656,
      "oblast": "Dnipropetrovsk",
      "sector": "energy_and_power",
      "lifecycle": "assessed",
      "destruction_level": "severe",
      "rebuildability": "rebuildable",
      "re_damage_count": 1,
      "pending_methodology": false,
      "financing_class": "concessional_led",
      "cost_baseline_low": 312,
      "cost_baseline_cen": 492,
      "cost_baseline_high": 672,
      "cost_cc_low": 359,
      "cost_cc_cen": 601,
      "cost_cc_high": 843,
      "cost_bbb_low": 406,
      "cost_bbb_cen": 738,
      "cost_bbb_high": 1070
    },
    {
      "asset_id": "SALTIVKA_DISTRICT_KHARKIV_2022_02_24",
      "name_en": "Saltivka Residential District, Kharkiv",
      "name_uk": "Жилий масив Салтівка, Харків",
      "lat": 50.035,
      "lon": 36.31,
      "oblast": "Kharkiv",
      "sector": "residential",
      "lifecycle": "assessed",
      "destruction_level": "moderate",
      "rebuildability": "rebuildable",
      "re_damage_count": 8,
      "pending_methodology": false,
      "financing_class": "concessional_led",
      "cost_baseline_low": 1339,
      "cost_baseline_cen": 3445,
      "cost_baseline_high": 5550,
      "cost_cc_low": 1540,
      "cost_cc_cen": 4239,
      "cost_cc_high": 6938,
      "cost_bbb_low": 1741,
      "cost_bbb_cen": 5311,
      "cost_bbb_high": 8880
    },
    {
      "asset_id": "SIEVIERODONETSK_RESIDENTIAL_2022_06_24",
      "name_en": "Sievierodonetsk City Residential — Pre-occupation Damage",
      "name_uk": "Житловий фонд Сєвєродонецька — пошкодження до окупації",
      "lat": 48.9514,
      "lon": 38.4762,
      "oblast": "Luhansk",
      "sector": "residential",
      "lifecycle": "documented",
      "destruction_level": "destroyed",
      "rebuildability": "recently_liberated",
      "re_damage_count": 2,
      "pending_methodology": false,
      "financing_class": "concessional_led",
      "cost_baseline_low": 991,
      "cost_baseline_cen": 1827,
      "cost_baseline_high": 2662,
      "cost_cc_low": 1139,
      "cost_cc_cen": 2233,
      "cost_cc_high": 3327,
      "cost_bbb_low": 1288,
      "cost_bbb_cen": 2774,
      "cost_bbb_high": 4259
    },
    {
      "asset_id": "SKOVORODA_MUSEUM_2022_05_06",
      "name_en": "H.S. Skovoroda National Literary-Memorial Museum, Skovorodynivka",
      "name_uk": "Національний літературно-меморіальний музей Г.С. Сковороди, Сковородинівка",
      "lat": 49.945,
      "lon": 36.281,
      "oblast": "Kharkiv",
      "sector": "heritage_and_culture",
      "lifecycle": "assessed",
      "destruction_level": "destroyed",
      "rebuildability": "rebuildable",
      "re_damage_count": 0,
      "pending_methodology": false,
      "financing_class": "concessional_led",
      "cost_baseline_low": 19,
      "cost_baseline_cen": 54,
      "cost_baseline_high": 90,
      "cost_cc_low": 22,
      "cost_cc_cen": 67,
      "cost_cc_high": 112,
      "cost_bbb_low": 25,
      "cost_bbb_cen": 84,
      "cost_bbb_high": 144
    },
    {
      "asset_id": "SLOVIANSK_CHP_2022_04_14",
      "name_en": "Sloviansk Combined Heat and Power Plant",
      "name_uk": "Слов'янська ТЕЦ",
      "lat": 48.8614,
      "lon": 37.6153,
      "oblast": "Donetsk",
      "sector": "energy_and_power",
      "lifecycle": "documented",
      "destruction_level": "destroyed",
      "rebuildability": "recently_liberated",
      "re_damage_count": 3,
      "pending_methodology": false,
      "financing_class": "concessional_led",
      "cost_baseline_low": 108,
      "cost_baseline_cen": 189,
      "cost_baseline_high": 270,
      "cost_cc_low": 124,
      "cost_cc_cen": 231,
      "cost_cc_high": 337,
      "cost_bbb_low": 140,
      "cost_bbb_cen": 284,
      "cost_bbb_high": 428
    },
    {
      "asset_id": "SLOVIANSK_SCHOOL_COMPLEX_2022_04_14",
      "name_en": "Sloviansk Secondary School Complex",
      "name_uk": "Слов'янський шкільний комплекс",
      "lat": 48.8602,
      "lon": 37.6071,
      "oblast": "Donetsk",
      "sector": "education",
      "lifecycle": "assessed",
      "destruction_level": "severe",
      "rebuildability": "rebuildable",
      "re_damage_count": 2,
      "pending_methodology": false,
      "financing_class": "grant_led",
      "cost_baseline_low": 14,
      "cost_baseline_cen": 24,
      "cost_baseline_high": 35,
      "cost_cc_low": 16,
      "cost_cc_cen": 29,
      "cost_cc_high": 43,
      "cost_bbb_low": 18,
      "cost_bbb_cen": 36,
      "cost_bbb_high": 54
    },
    {
      "asset_id": "SUMY_RESIDENTIAL_2022_03_01",
      "name_en": "Sumy City Northern Residential Districts",
      "name_uk": "Північні житлові райони Сум",
      "lat": 50.9077,
      "lon": 34.7981,
      "oblast": "Sumy",
      "sector": "residential",
      "lifecycle": "assessed",
      "destruction_level": "light",
      "rebuildability": "rebuildable",
      "re_damage_count": 0,
      "pending_methodology": false,
      "financing_class": "concessional_led",
      "cost_baseline_low": 17,
      "cost_baseline_cen": 57,
      "cost_baseline_high": 97,
      "cost_cc_low": 20,
      "cost_cc_cen": 71,
      "cost_cc_high": 121,
      "cost_bbb_low": 22,
      "cost_bbb_cen": 89,
      "cost_bbb_high": 155
    },
    {
      "asset_id": "SVIATOHIRSK_LAVRA_2022_05_30",
      "name_en": "Sviatohirsk Holy Dormition Lavra",
      "name_uk": "Свято-Успенська Святогірська лавра",
      "lat": 49.0572,
      "lon": 37.5503,
      "oblast": "Donetsk",
      "sector": "heritage_and_culture",
      "lifecycle": "assessed",
      "destruction_level": "severe",
      "rebuildability": "frontline_adjacent",
      "re_damage_count": 2,
      "pending_methodology": false,
      "financing_class": "concessional_led",
      "cost_baseline_low": 181,
      "cost_baseline_cen": 884,
      "cost_baseline_high": 1587,
      "cost_cc_low": 208,
      "cost_cc_cen": 1096,
      "cost_cc_high": 1984,
      "cost_bbb_low": 235,
      "cost_bbb_cen": 1388,
      "cost_bbb_high": 2540
    },
    {
      "asset_id": "TRYPILSKA_TPP_2024_04_11",
      "name_en": "Trypilska Thermal Power Plant",
      "name_uk": "Трипільська теплова електростанція",
      "lat": 50.1073,
      "lon": 30.7636,
      "oblast": "Kyiv",
      "sector": "energy_and_power",
      "lifecycle": "assessed",
      "destruction_level": "destroyed",
      "rebuildability": "rebuildable",
      "re_damage_count": 0,
      "pending_methodology": false,
      "financing_class": "concessional_led",
      "cost_baseline_low": 747,
      "cost_baseline_cen": 1330,
      "cost_baseline_high": 1913,
      "cost_cc_low": 859,
      "cost_cc_cen": 1625,
      "cost_cc_high": 2391,
      "cost_bbb_low": 971,
      "cost_bbb_cen": 2016,
      "cost_bbb_high": 3060
    },
    {
      "asset_id": "UKRENERGO_PIVNICHNA_SUBSTATION_2024_03_22",
      "name_en": "Ukrenergo Pivnichna 750kV Substation",
      "name_uk": "Підстанція «Північна» 750 кВ НЕК Укренерго",
      "lat": 50.72,
      "lon": 30.45,
      "oblast": "Kyiv",
      "sector": "energy_and_power",
      "lifecycle": "assessed",
      "destruction_level": "severe",
      "rebuildability": "rebuildable",
      "re_damage_count": 2,
      "pending_methodology": false,
      "financing_class": "concessional_led",
      "cost_baseline_low": 39,
      "cost_baseline_cen": 97,
      "cost_baseline_high": 154,
      "cost_cc_low": 45,
      "cost_cc_cen": 119,
      "cost_cc_high": 192,
      "cost_bbb_low": 51,
      "cost_bbb_cen": 149,
      "cost_bbb_high": 246
    },
    {
      "asset_id": "VINNYTSIA_CHPP_2022_07_14",
      "name_en": "Vinnytsia Combined Heat and Power Plant",
      "name_uk": "Вінницька ТЕЦ",
      "lat": 49.2328,
      "lon": 28.4753,
      "oblast": "Vinnytsia",
      "sector": "energy_and_power",
      "lifecycle": "assessed",
      "destruction_level": "moderate",
      "rebuildability": "rebuildable",
      "re_damage_count": 0,
      "pending_methodology": false,
      "financing_class": "concessional_led",
      "cost_baseline_low": 38,
      "cost_baseline_cen": 62,
      "cost_baseline_high": 86,
      "cost_cc_low": 44,
      "cost_cc_cen": 76,
      "cost_cc_high": 107,
      "cost_bbb_low": 50,
      "cost_bbb_cen": 93,
      "cost_bbb_high": 136
    },
    {
      "asset_id": "VINNYTSIA_REGIONAL_HOSPITAL_2022_07_14",
      "name_en": "Vinnytsia Regional Clinical Hospital named after M. Pirogov",
      "name_uk": "Вінницька обласна клінічна лікарня ім. М.І.Пирогова",
      "lat": 49.243,
      "lon": 28.452,
      "oblast": "Vinnytsia",
      "sector": "healthcare",
      "lifecycle": "assessed",
      "destruction_level": "severe",
      "rebuildability": "rebuildable",
      "re_damage_count": 0,
      "pending_methodology": false,
      "financing_class": "concessional_led",
      "cost_baseline_low": 94,
      "cost_baseline_cen": 164,
      "cost_baseline_high": 234,
      "cost_cc_low": 109,
      "cost_cc_cen": 201,
      "cost_cc_high": 293,
      "cost_bbb_low": 123,
      "cost_bbb_cen": 249,
      "cost_bbb_high": 374
    },
    {
      "asset_id": "VOLNOVAKHA_RESIDENTIAL_2022_03_12",
      "name_en": "Volnovakha Town Residential — Donetsk Oblast",
      "name_uk": "Житловий фонд міста Волноваха — Донецька область",
      "lat": 47.5977,
      "lon": 37.4963,
      "oblast": "Donetsk",
      "sector": "residential",
      "lifecycle": "documented",
      "destruction_level": "destroyed",
      "rebuildability": "recently_liberated",
      "re_damage_count": 0,
      "pending_methodology": false,
      "financing_class": "concessional_led",
      "cost_baseline_low": 156,
      "cost_baseline_cen": 288,
      "cost_baseline_high": 419,
      "cost_cc_low": 179,
      "cost_cc_cen": 351,
      "cost_cc_high": 523,
      "cost_bbb_low": 203,
      "cost_bbb_cen": 437,
      "cost_bbb_high": 670
    },
    {
      "asset_id": "VUHLEDAR_RESIDENTIAL_2023_02_01",
      "name_en": "Vuhledar Housing District",
      "name_uk": "Вугледар — житловий фонд міста",
      "lat": 47.7664,
      "lon": 37.2522,
      "oblast": "Donetsk",
      "sector": "residential",
      "lifecycle": "documented",
      "destruction_level": "destroyed",
      "rebuildability": "occupied",
      "re_damage_count": 5,
      "pending_methodology": false,
      "financing_class": "blended",
      "cost_baseline_low": 107,
      "cost_baseline_cen": 210,
      "cost_baseline_high": 313,
      "cost_cc_low": 123,
      "cost_cc_cen": 257,
      "cost_cc_high": 391,
      "cost_bbb_low": 139,
      "cost_bbb_cen": 315,
      "cost_bbb_high": 491
    },
    {
      "asset_id": "ZAPORIZHZHIA_ANTONIVKA_BRIDGE_2022_10_20",
      "name_en": "Zaporizhzhia Road Bridge over the Dnipro (Preobrazhenka)",
      "name_uk": "Запорізький автомобільний міст через Дніпро (Преображенка)",
      "lat": 47.802,
      "lon": 35.089,
      "oblast": "Zaporizhzhia",
      "sector": "transport_and_ports",
      "lifecycle": "assessed",
      "destruction_level": "moderate",
      "rebuildability": "rebuildable",
      "re_damage_count": 1,
      "pending_methodology": false,
      "financing_class": "concessional_led",
      "cost_baseline_low": 35,
      "cost_baseline_cen": 58,
      "cost_baseline_high": 81,
      "cost_cc_low": 40,
      "cost_cc_cen": 71,
      "cost_cc_high": 101,
      "cost_bbb_low": 46,
      "cost_bbb_cen": 87,
      "cost_bbb_high": 128
    },
    {
      "asset_id": "ZAPORIZHZHIA_POBYEDA_RESIDENTIAL_2022_03_01",
      "name_en": "Pobyeda District Residential, Zaporizhzhia City",
      "name_uk": "Жилий масив «Перемога», Запоріжжя",
      "lat": 47.8388,
      "lon": 35.1396,
      "oblast": "Zaporizhzhia",
      "sector": "residential",
      "lifecycle": "assessed",
      "destruction_level": "moderate",
      "rebuildability": "rebuildable",
      "re_damage_count": 0,
      "pending_methodology": false,
      "financing_class": "concessional_led",
      "cost_baseline_low": 295,
      "cost_baseline_cen": 779,
      "cost_baseline_high": 1262,
      "cost_cc_low": 339,
      "cost_cc_cen": 958,
      "cost_cc_high": 1577,
      "cost_bbb_low": 383,
      "cost_bbb_cen": 1201,
      "cost_bbb_high": 2019
    },
    {
      "asset_id": "ZAPORIZHZHIA_POLYTECHNIC_2022_10_09",
      "name_en": "Zaporizhzhia National Technical University (ZNTU)",
      "name_uk": "Запорізький національний технічний університет (ЗНТУ)",
      "lat": 47.8374,
      "lon": 35.1487,
      "oblast": "Zaporizhzhia",
      "sector": "education",
      "lifecycle": "assessed",
      "destruction_level": "moderate",
      "rebuildability": "rebuildable",
      "re_damage_count": 1,
      "pending_methodology": false,
      "financing_class": "grant_led",
      "cost_baseline_low": 28,
      "cost_baseline_cen": 48,
      "cost_baseline_high": 69,
      "cost_cc_low": 32,
      "cost_cc_cen": 59,
      "cost_cc_high": 86,
      "cost_bbb_low": 36,
      "cost_bbb_cen": 73,
      "cost_bbb_high": 110
    },
    {
      "asset_id": "ZAPORIZHZHIA_REGIONAL_HOSPITAL_2022_10_09",
      "name_en": "Zaporizhzhia Regional Clinical Hospital",
      "name_uk": "Запорізька обласна клінічна лікарня",
      "lat": 47.8388,
      "lon": 35.1396,
      "oblast": "Zaporizhzhia",
      "sector": "healthcare",
      "lifecycle": "assessed",
      "destruction_level": "moderate",
      "rebuildability": "rebuildable",
      "re_damage_count": 2,
      "pending_methodology": false,
      "financing_class": "concessional_led",
      "cost_baseline_low": 58,
      "cost_baseline_cen": 101,
      "cost_baseline_high": 144,
      "cost_cc_low": 67,
      "cost_cc_cen": 123,
      "cost_cc_high": 180,
      "cost_bbb_low": 76,
      "cost_bbb_cen": 152,
      "cost_bbb_high": 228
    },
    {
      "asset_id": "ZAPORIZHZHIA_WATER_SUPPLY_2022_10_01",
      "name_en": "Zaporizhzhia City Water Supply System",
      "name_uk": "Запорізька міська система водопостачання",
      "lat": 47.8428,
      "lon": 35.1432,
      "oblast": "Zaporizhzhia",
      "sector": "water_and_sanitation",
      "lifecycle": "assessed",
      "destruction_level": "moderate",
      "rebuildability": "rebuildable",
      "re_damage_count": 3,
      "pending_methodology": false,
      "financing_class": "grant_led",
      "cost_baseline_low": 58,
      "cost_baseline_cen": 96,
      "cost_baseline_high": 134,
      "cost_cc_low": 67,
      "cost_cc_cen": 117,
      "cost_cc_high": 167,
      "cost_bbb_low": 76,
      "cost_bbb_cen": 144,
      "cost_bbb_high": 212
    },
    {
      "asset_id": "ZMIIVSKA_TPP_2024_03_22",
      "name_en": "Zmiivska Thermal Power Plant",
      "name_uk": "Змієвська теплова електростанція",
      "lat": 49.66,
      "lon": 36.38,
      "oblast": "Kharkiv",
      "sector": "energy_and_power",
      "lifecycle": "assessed",
      "destruction_level": "destroyed",
      "rebuildability": "rebuildable",
      "re_damage_count": 2,
      "pending_methodology": false,
      "financing_class": "concessional_led",
      "cost_baseline_low": 1206,
      "cost_baseline_cen": 2182,
      "cost_baseline_high": 3157,
      "cost_cc_low": 1387,
      "cost_cc_cen": 2667,
      "cost_cc_high": 3947,
      "cost_bbb_low": 1568,
      "cost_bbb_cen": 3310,
      "cost_bbb_high": 5052
    }
  ]
}
